{
  "$schema": "https://json.schemastore.org/tsconfig",
  "compilerOptions": {
    "target": "ESNext",
    "module": "ESNext",
    "moduleResolution": "Bundler",
    "declaration": true,
    "declarationMap": true,
    "esModuleInterop": true,
    "allowImportingTsExtensions": true,
    "resolveJsonModule": true,
    "verbatimModuleSyntax": true,
    "isolatedModules": true,
    "noEmit": true,
    "forceConsistentCasingInFileNames": true,
    "skipLibCheck": true,
    "allowJs": true
  },
  "exclude": ["node_modules"]
}
